aida_ua/__init__.py
aida_ua/main.py
aida_ua-0.1.0.dist-info/METADATA
aida_ua-0.1.0.dist-info/WHEEL
aida_ua-0.1.0.dist-info/RECORD
