Metadata-Version: 2.1
Name: aida-ua
Version: 0.1.0
Summary: 
Author: Dmytro Lyfenko
Author-email: 114363730+Lyfenko@users.noreply.github.com
Requires-Python: >=3.11,<4.0
Classifier: Programming Language :: Python :: 3
Classifier: Programming Language :: Python :: 3.11
Requires-Dist: aiohttp (>=3.8.4,<4.0.0)
Requires-Dist: flask (>=2.2.3,<3.0.0)
